{
    "duration_s": 12.171815000008792,
    "meta_version": "2.3",
    "min_player_version": "2.0",
    "recording_name": "E:/UnityProjects/VRCarSimulator/VRCarSimulator/2024_02_09",
    "recording_software_name": "Pupil Capture",
    "recording_software_version": "3.5.1",
    "recording_uuid": "14312976-4f09-43f2-a3d5-5b0bc2cd48ac",
    "start_time_synced_s": 682295.795774,
    "start_time_system_s": 1707497692.315524,
    "system_info": "User: Dawid, Platform: Windows, Machine: DESKTOP-6N1K5A4, Release: 10, Version: 10.0.19041"
}